cfdb/__init__.py
cfdb/combine.py
cfdb/core.py
cfdb/creation.py
cfdb/data_models.py
cfdb/dtypes.py
cfdb/indexers.py
cfdb/main.py
cfdb/support_classes.py
cfdb/tools.py
cfdb/utils.py
cfdb-0.1.2.dist-info/METADATA
cfdb-0.1.2.dist-info/WHEEL
cfdb-0.1.2.dist-info/licenses/LICENSE
cfdb-0.1.2.dist-info/RECORD
