Metadata-Version: 2.4
Name: cfdb
Version: 0.1.2
Summary: CF conventions multi-dimensional array storage on top of Booklet
Project-URL: Documentation, https://mullenkamp.github.io/cfdb/
Project-URL: Source, https://github.com/mullenkamp/cfdb
Author-email: mullenkamp <mullenkamp1@gmail.com>
License-File: LICENSE
Classifier: Programming Language :: Python :: 3 :: Only
Requires-Python: >=3.10
Requires-Dist: booklet>=0.9.2
Requires-Dist: lz4
Requires-Dist: msgspec
Requires-Dist: numpy>2
Requires-Dist: pyproj>3
Requires-Dist: rechunkit>=0.1.2
Requires-Dist: shapely>2
Requires-Dist: zstandard
Provides-Extra: ebooklet
Requires-Dist: ebooklet>=0.5.10; extra == 'ebooklet'
Provides-Extra: netcdf4
Requires-Dist: cftime; extra == 'netcdf4'
Requires-Dist: h5netcdf; extra == 'netcdf4'
